setup.py
dedup/__init__.py
dedup/__main__.py
dedup/dedup.py
dedup/file.py
dedup.egg-info/PKG-INFO
dedup.egg-info/SOURCES.txt
dedup.egg-info/dependency_links.txt
dedup.egg-info/entry_points.txt
dedup.egg-info/requires.txt
dedup.egg-info/top_level.txt