Metadata-Version: 1.1
Name: dedup
Version: 0.0.1
Summary: dedup
Home-page: https://github.com/bchiang2/dedup
Author: Ben
Author-email: UNKNOWN
License: UNKNOWN
Platform: UNKNOWN
Classifier: Development Status :: 3 - Alpha
Classifier: Intended Audience :: Developers
Classifier: Programming Language :: Python :: 3
